{
  "algorithm": {
    "general": {
      "title": "Running tool for predictors",
      "web-site": "",
      "source": "Python library developed by ARPAL and CIMA Research Foundation",
      "history": "1.4.0 [20250724]",
      "project-info": "sliper",
      "algorithm": "Algorithm developed by ARPAL and CIMA Research Foundation"
    },
    "flags": {
      "update_static": true,
      "update_dynamic_ancillary": true,
      "update_dynamic_destination": true
    },
    "parameters": {
      "__comment__": "running_mode values: fx_kernel",
      "methods": {
        "fx_kernel" : {"kernel_type":  "polynomial", "kernel_exponent": 3, "active": true}
      },
      "analysis": {
        "variables": {
          "var_1": "sm_value_first",
          "var_2": "rain_accumulated_12H",
          "var_3": "rain_peak_3H"},
        "time": {
          "time_period": null,
          "time_frequency": "D",
          "time_rounding": "D",
          "time_start": null,
          "time_end": null
        }
      },
      "columns_names": [
            "time", "sm_value_first",
            "rain_accumulated_12H", "rain_peak_3H",
            "event_n", "event_threshold", "event_index", "event_domain"]
    },
    "template": {
      "domain_name": "string_domain",
      "alert_area_name": "string_alert_area",
      "run_datetime": "%Y%m%d",
      "run_sub_path_time": "%Y/%m/%d/",
      "source_sub_path_time": "%Y/%m/%d/",
      "source_datetime": "%Y%m%d%H%M",
      "source_datetime_from": "from_%Y%m%d%H%M",
      "source_datetime_to": "to_%Y%m%d%H%M",
      "ancillary_sub_path_time": "%Y/%m/%d/",
      "ancillary_datetime": "%Y%m%d%H%M",
      "destination_sub_path_time": "%Y/%m/%d/",
      "destination_datetime": "%Y%m%d%H%M"
    }
  },
  "data": {
    "static" : {
      "source": {
        "geo_datasets": {
          "folder_name": "/home/fabio/Desktop/sliper/ws/data_static/alert_area/",
          "file_name": "alert_area_info.csv",
          "type": "vector",
          "format": "csv"
        },
        "training_datasets": {
          "training_matrix_center": {
            "folder_name": "/home/fabio/Desktop/PyCharm_ARPAL/soilslips-ws/data_static/training_predictors/",
            "file_name": "Xtr_centered.csv"
          },
          "training_matrix_max": {
            "folder_name": "/home/fabio/Desktop/PyCharm_ARPAL/soilslips-ws/data_static/training_predictors/",
            "file_name": "Xtr_max.csv"
          },
          "training_matrix_mean": {
            "folder_name": "/home/fabio/Desktop/PyCharm_ARPAL/soilslips-ws/data_static/training_predictors/",
            "file_name": "Xtrn_mean.csv"
          },
          "training_coefficient": {
            "folder_name": "/home/fabio/Desktop/PyCharm_ARPAL/soilslips-ws/data_static/training_predictors/",
            "file_name": "C_coefficients.csv"
          }
        }
      },
      "destination": {
        "training_datasets": {
          "folder_name": "/home/fabio/Desktop/Workspace/sliper/ws/data_static/workspace/",
          "file_name": "training_info_predictors.workspace",
          "type": "vector",
          "format": "workspace"
        },
        "geo_datasets": {
          "folder_name": "/home/fabio/Desktop/Workspace/sliper/ws/data_static/workspace/",
          "file_name": "geo_info_predictors.workspace",
          "type": "vector",
          "format": "workspace"
        }
      }
    },
    "dynamic": {
      "source": {
        "folder_name": "/home/fabio/Desktop/Workspace/sliper/ws/data_dynamic/destination/scenarios/{source_sub_path_time}",
        "file_name": "scenarios_{source_datetime}_{alert_area_name}.csv",
        "type": "vector",
        "format": "csv",
        "delimiter": ";",
        "variable": ["rain", "soil_moisture", "soil_slips"],
        "prefix": ["rain", "sm", "slips"],
        "fields": {
          "time": "time",
          "domain": "domain",
          "rain_peak_3H": "rain_peak_3H:max",
          "rain_accumulated_12H": "rain_accumulated_12H:max",
          "rain_time_run": "rain_time_run",
          "rain_time_start": "rain_time_start",
          "rain_time_end": "rain_time_end",
          "rain_period_type": "rain_period_type",
          "rain_latest_from": "rain_latest_from",
          "sm_value_first": "sm_value_first",
          "sm_value_last": "sm_value_last",
          "sm_time_run": "sm_time_run",
          "sm_time_start": "sm_time_start",
          "sm_time_end": "sm_time_end",
          "sm_period_type": "sm_period_type",
          "sm_latest_from": "sm_latest_from",
          "slips_domain": "slips_area_label",
          "slips_obs_n": "slips_n",
          "slips_obs_id": "slips_id",
          "slips_obs_alert_color": "slips_alert_color",
          "slips_obs_alert_rgb": "slips_alert_rgb"
        }
      },
      "ancillary": {
        "folder_name": "/home/fabio/Desktop/Workspace/sliper/ws/data_dynamic/ancillary/predictors/{ancillary_sub_path_time}",
        "file_name": "predictors_{ancillary_datetime}_{alert_area_name}.workspace"
      },
      "destination": {
        "folder_name": "/home/fabio/Desktop/Workspace/sliper/ws/data_dynamic/destination/predictors/{destination_sub_path_time}",
        "file_name": "predictors_{destination_datetime}_{alert_area_name}.csv",
        "type": "vector",
        "format": "csv",
        "delimiter": ";",
        "variable": ["rain", "soil_moisture", "soil_slips"],
        "prefix": ["rain", "sm", "slips"],
        "fields": {
          "time": "time",
          "day_of_the_year": "day_of_the_year",
          "rain_peak_3H": "rain_peak_3H",
          "rain_accumulated_12H": "rain_accumulated_12H",
          "rain_time_run": "rain_time_run",
          "rain_time_start": "rain_time_start",
          "rain_time_end": "rain_time_end",
          "rain_period_type": "rain_period_type",
          "rain_latest_from": null,
          "sm_value_first": "sm_value_first",
          "sm_value_last": "sm_value_last",
          "sm_time_run": "sm_time_run",
          "sm_time_start": "sm_time_start",
          "sm_time_end": "sm_time_end",
          "sm_period_type": "sm_period_type",
          "sm_latest_from": null,
          "slips_domain": "soil_slips_domain",
          "slips_obs_n": "soil_slips_obs_n",
          "slips_obs_id": "soil_slips_obs_id",
          "slips_obs_alert_level": "soil_slips_pred_alert_level",
          "slips_obs_alert_color": "soil_slips_obs_alert_color",
          "slips_obs_alert_rgb": "soil_slips_obs_alert_rgb",
          "slips_pred_n": "soil_slips_pred_n",
          "slips_pred_id": "soil_slips_pred_id",
          "slips_pred_alert_level": "soil_slips_pred_alert_level",
          "slips_pred_alert_color": "soil_slips_pred_alert_color",
          "slips_pred_alert_rgb": "soil_slips_pred_alert_rgb"
        }
      }
    }
  },
  "tmp": {
    "folder_name": "/home/fabio/Desktop/Workspace/sliper/ws/tmp/",
    "file_name": null
  },
  "log": {
    "folder_name": "/home/fabio/Desktop/Workspace/sliper/ws/log/",
    "file_name": "sliper_predictors_log.txt"
  },
  "time": {
    "time_now": null,
    "time_period": 2,
    "time_frequency": "D",
    "time_rounding": "D",
    "time_start": "2023-01-12 00:00",
    "time_end": "2023-01-12 00:00"
  }
}
